{
  "companyInfo": {
    "Tên quốc tế": "DUXO BABY COMPANY LIMITED",
    "Tên viết tắt": "DUXO BABY.,LTD",
    "Mã số thuế": "0110608880",
    "Địa chỉ": "Số 8A, Ngõ 1197 đường Giải Phóng, Phường Thịnh Liệt, Quận Hoàng Mai, Thành phố Hà Nội, Việt Nam",
    "Người đại diện": "VŨ THANH HUYỀN ( sinh năm 1994 - Hà Nội) Ẩn thông tin ",
    "Điện thoại": " 0397726166",
    "Ngày hoạt động": "2024-01-22",
    "Quản lý bởi": "Chi cục thuế Quận Hoàng Mai",
    "Loại hình DN": "Công ty trách nhiệm hữu hạn 2 thành viên trở lên ngoài NN",
    "Tình trạng": "Đang hoạt động (đã được cấp GCN ĐKT)"
  },
  "industryInfo": {
    "4631": "Bán buôn gạo",
    "4632": "Bán buôn thực phẩm",
    "4633": "Bán buôn đồ uống",
    "4641": "Bán buôn vải, hàng may sẵn, giày dép",
    "4649": "Bán buôn đồ dùng khác cho gia đình",
    "4652": "Bán buôn thiết bị và linh kiện điện tử, viễn thông",
    "4659": "Bán buôn máy móc, thiết bị và phụ tùng máy khác",
    "4669": "Bán buôn chuyên doanh khác chưa được phân vào đâu",
    "4690": "Bán buôn tổng hợp",
    "4711": "Bán lẻ lương thực, thực phẩm, đồ uống, thuốc lá, thuốc lào chiếm tỷ trọng lớn trong các cửa hàng kinh doanh tổng hợp",
    "4719": "Bán lẻ khác trong các cửa hàng kinh doanh tổng hợp",
    "4721": "Bán lẻ lương thực trong các cửa hàng chuyên doanh",
    "4722": "Bán lẻ thực phẩm trong các cửa hàng chuyên doanh",
    "4723": "Bán lẻ đồ uống trong các cửa hàng chuyên doanh",
    "4751": "Bán lẻ vải, len, sợi, chỉ khâu và hàng dệt khác trong các cửa hàng chuyên doanh",
    "4752": "Bán lẻ đồ ngũ kim, sơn, kính và thiết bị lắp đặt khác trong xây dựng trong các cửa hàng chuyên doanh",
    "4753": "Bán lẻ thảm, đệm, chăn, màn, rèm, vật liệu phủ tường và sàn trong các cửa hàng chuyên doanh",
    "4759": "Bán lẻ đồ điện gia dụng, giường, tủ, bàn, ghế và đồ nội thất tương tự, đèn và bộ đèn điện, đồ dùng gia đình khác chưa được phân vào đâu trong các cửa hàng chuyên doanh",
    "4761": "Bán lẻ sách, báo, tạp chí văn phòng phẩm trong các cửa hàng chuyên doanh",
    "4763": "Bán lẻ thiết bị, dụng cụ thể dục, thể thao trong các cửa hàng chuyên doanh",
    "4764": "Bán lẻ trò chơi, đồ chơi trong các cửa hàng chuyên doanh",
    "4771": "Bán lẻ hàng may mặc, giày dép, hàng da và giả da trong các cửa hàng chuyên doanh",
    "4772": "Bán lẻ thuốc, dụng cụ y tế, mỹ phẩm và vật phẩm vệ sinh trong các cửa hàng chuyên doanh",
    "4773": "Bán lẻ hàng hóa khác mới trong các cửa hàng chuyên doanh",
    "4791": "Bán lẻ theo yêu cầu đặt hàng qua bưu điện hoặc internet",
    "5225": "Hoạt động dịch vụ hỗ trợ trực tiếp cho vận tải đường bộ",
    "5229": "Hoạt động dịch vụ hỗ trợ khác liên quan đến vận tải",
    "8292": "Dịch vụ đóng gói",
    "8299": "Hoạt động dịch vụ hỗ trợ kinh doanh khác còn lại chưa được phân vào đâu"
  }
}